webpath/__init__.py
webpath/_http.py
webpath/cache.py
webpath/cli.py
webpath/core.py
webpath-0.0.2.dist-info/METADATA
webpath-0.0.2.dist-info/WHEEL
webpath-0.0.2.dist-info/entry_points.txt
webpath-0.0.2.dist-info/top_level.txt
webpath-0.0.2.dist-info/RECORD
