Metadata-Version: 2.4
Name: webpath
Version: 0.0.2
Summary: Pathlib-like library for building URLs and making API calls
Author-email: oha <aaronoh2015@gmail.com>
Project-URL: Homepage, https://github.com/duriantaco/webpath
Requires-Python: >=3.8
Requires-Dist: typer>=0.16.0
Requires-Dist: rich>=14.0.0
Requires-Dist: pydantic
Requires-Dist: jmespath
Requires-Dist: httpx>=0.27
Provides-Extra: async
Requires-Dist: httpx>=0.27; extra == "async"
Provides-Extra: progress
Requires-Dist: tqdm>=4.66; extra == "progress"
Provides-Extra: dev
Requires-Dist: pytest>=7.4; extra == "dev"
Requires-Dist: requests_mock>=1.12; extra == "dev"
Requires-Dist: tqdm>=4.66; extra == "dev"
Requires-Dist: httpx>=0.28; extra == "dev"
